kanvas/__init__.py
kanvas/__main__.py
kanvas/controller.py
kanvas/core.py
kanvas/model.py
kanvas/utils.py
kanvas/view.py
kanvas-0.1.6.dist-info/METADATA
kanvas-0.1.6.dist-info/WHEEL
kanvas-0.1.6.dist-info/top_level.txt
kanvas-0.1.6.dist-info/RECORD
