Metadata-Version: 2.4
Name: kanvas
Version: 0.1.6
Summary: A minimalist creative-coding toolkit for Python (homage to Processing/p5).
Author: Robin Oscarsson
License: MIT
Project-URL: Homepage, https://github.com/robinoscarsson/kanvas
Project-URL: Issues, https://github.com/robinoscarsson/kanvas/issues
Requires-Python: >=3.9
Requires-Dist: pygame>=2.0
Requires-Dist: numpy>=1.23
